de_toolkit/__init__.py
de_toolkit/common.py
de_toolkit/de.py
de_toolkit/enrich.py
de_toolkit/filter.py
de_toolkit/norm.py
de_toolkit/outlier.py
de_toolkit/patsy_lite.py
de_toolkit/report.py
de_toolkit/stats.py
de_toolkit/test_docopt.py
de_toolkit/transform.py
de_toolkit/util.py
de_toolkit/version.py
de_toolkit/wrapr.py
de_toolkit/templates/css/colzero.css
de_toolkit/templates/css/common.css
de_toolkit/templates/css/entropy.css
de_toolkit/templates/css/filtercounts.css
de_toolkit/templates/css/pca.css
de_toolkit/templates/css/assets/bootstrap.min.css
de_toolkit/templates/css/assets/droid-sans.css
de_toolkit/templates/css/assets/jquery-ui/jquery-ui.min.css
de_toolkit/templates/css/assets/jquery-ui/jquery-ui.structure.min.css
de_toolkit/templates/css/assets/jquery-ui/jquery-ui.theme.min.css
de_toolkit/templates/html/base.html
de_toolkit/templates/html/base_dev.html
de_toolkit/templates/html/basestats.html
de_toolkit/templates/html/coldist.html
de_toolkit/templates/html/colzero.html
de_toolkit/templates/html/common.html
de_toolkit/templates/html/entropy.html
de_toolkit/templates/html/filtercounts.html
de_toolkit/templates/html/pca.html
de_toolkit/templates/html/rowdist.html
de_toolkit/templates/html/rowzero.html
de_toolkit/templates/js/coldist.js
de_toolkit/templates/js/colzero.js
de_toolkit/templates/js/common.js
de_toolkit/templates/js/entropy.js
de_toolkit/templates/js/filtercounts.js
de_toolkit/templates/js/pca.js
de_toolkit/templates/js/rowzero.js
de_toolkit/templates/js/assets/bootstrap.bundle.min.js
de_toolkit/templates/js/assets/d3-array.v1.min.js
de_toolkit/templates/js/assets/d3-collection.v1.min.js
de_toolkit/templates/js/assets/d3-color.v1.min.js
de_toolkit/templates/js/assets/d3-format.v1.min.js
de_toolkit/templates/js/assets/d3-interpolate.v1.min.js
de_toolkit/templates/js/assets/d3-scale.v2.min.js
de_toolkit/templates/js/assets/doT.min.js
de_toolkit/templates/js/assets/underscore-min.js
de_toolkit-0.9.12.dist-info/DESCRIPTION.rst
de_toolkit-0.9.12.dist-info/METADATA
de_toolkit-0.9.12.dist-info/RECORD
de_toolkit-0.9.12.dist-info/WHEEL
de_toolkit-0.9.12.dist-info/entry_points.txt
de_toolkit-0.9.12.dist-info/metadata.json
de_toolkit-0.9.12.dist-info/top_level.txt
