Metadata-Version: 2.0
Name: de-toolkit
Version: 0.9.12
Summary: Suite of tools for working with count data
Home-page: https://bitbucket.org/bubioinformaticshub/de_toolkit
Author: Adam Labadorf and the BU Bioinformatics Hub Team
Author-email: labadorf@bu.edu
License: MIT
Keywords: bioinformatics,biology,sequencing,NGS
Platform: UNKNOWN
Classifier: Development Status :: 3 - Alpha
Classifier: Intended Audience :: Science/Research
Classifier: Environment :: Console
Classifier: License :: OSI Approved :: MIT License
Classifier: Programming Language :: Python :: 3
Classifier: Topic :: Scientific/Engineering :: Bio-Informatics
Requires-Python: ~=3.3
Requires-Dist: docopt
Requires-Dist: future
Requires-Dist: jinja2
Requires-Dist: numpy
Requires-Dist: pandas
Requires-Dist: patsy
Requires-Dist: ply
Requires-Dist: scikit-learn
Requires-Dist: scipy
Requires-Dist: setuptools
Requires-Dist: statsmodels (>=0.8.0)
Requires-Dist: terminaltables
